plutobio/__init__.py
plutobio/analyses.py
plutobio/api_endpoints.py
plutobio/assay_data.py
plutobio/attachments.py
plutobio/client.py
plutobio/download_upload.py
plutobio/experiments.py
plutobio/log_handler.py
plutobio/pipelines.py
plutobio/plots.py
plutobio/projects.py
plutobio/results.py
plutobio/sample_data.py
plutobio/settings.py
plutobio/utils.py
PlutoBio-0.1.13.dist-info/METADATA
PlutoBio-0.1.13.dist-info/WHEEL
PlutoBio-0.1.13.dist-info/top_level.txt
PlutoBio-0.1.13.dist-info/RECORD
