Metadata-Version: 2.1
Name: PlutoBio
Version: 0.1.13
Summary: A Python SDK for Pluto.bio
Author: Pluto Team
Keywords: PlutoBio,SDK,API,Biosciences,Pluto
Requires-Python: >=3.10, <4
Requires-Dist: requests
Requires-Dist: pandas
